setup.py
pp_transformers/__init__.py
pp_transformers/bert.py
pp_transformers/ernie.py
pp_transformers/nezha.py
pp_transformers/roberta.py
pp_transformers/roformer.py
pp_transformers/roformer2.py
pp_transformers/t5.py
pp_transformers/tokenizer.py
pp_transformers/utils.py
pp_transformers.egg-info/PKG-INFO
pp_transformers.egg-info/SOURCES.txt
pp_transformers.egg-info/dependency_links.txt
pp_transformers.egg-info/requires.txt
pp_transformers.egg-info/top_level.txt