Metadata-Version: 2.1
Name: pp-transformers
Version: 0.0.5
Summary: transformer of paddle
Author: bei
License: MIT Licence
Platform: UNKNOWN
